[{"id":308,"created_at":"2024-09-09 20:59:30","date":"2024-09-09","text":"十天后重新开放 channel 了，欢迎来视奸我哦 ❤️❤️❤️","photos":[],"tags":[],"quoted_message":null,"forwarded_info":null},{"id":307,"created_at":"2024-09-09 19:36:51","date":"2024-09-09","text":"日本游记：https://r.piggy.lol/2024/09/08/202409-travel-at-japan/\n\n但还没糊完","photos":[],"tags":[],"quoted_message":null,"forwarded_info":null},{"id":306,"created_at":"2024-09-09 18:42:56","date":"2024-09-09","text":"一周不见，这个同事还是一如既往的恶心呀","photos":[{"path":"306_20240909104256.jpg","width":434,"height":39,"id":306}],"tags":[],"quoted_message":null,"forwarded_info":null}]